{
  "cart": [
    {
      "id": "782b",
      "title": "Eggs",
      "description": "Fresh eggs, a versatile ingredient for baking, cooking, or breakfast.",
      "category": "groceries",
      "price": 2.99,
      "discountPercentage": 11.05,
      "rating": 2.53,
      "stock": 9,
      "tags": [
        "dairy"
      ],
      "sku": "GRO-BRD-EGG-023",
      "weight": 2,
      "dimensions": {
        "width": 11.42,
        "height": 7.44,
        "depth": 16.95
      },
      "warrantyInformation": "1 week warranty",
      "shippingInformation": "Ships in 1 week",
      "availabilityStatus": "In stock",
      "reviews": [
        {
          "rating": 3,
          "comment": "Disappointing product!",
          "date": "2025-04-30T09:41:02.053Z",
          "reviewerName": "Penelope King",
          "reviewerEmail": "penelope.king@x.dummyjson.com"
        },
        {
          "rating": 3,
          "comment": "Poor quality!",
          "date": "2025-04-30T09:41:02.053Z",
          "reviewerName": "Eleanor Tyler",
          "reviewerEmail": "eleanor.tyler@x.dummyjson.com"
        },
        {
          "rating": 4,
          "comment": "Very pleased!",
          "date": "2025-04-30T09:41:02.053Z",
          "reviewerName": "Benjamin Foster",
          "reviewerEmail": "benjamin.foster@x.dummyjson.com"
        }
      ],
      "returnPolicy": "No return policy",
      "minimumOrderQuantity": 32,
      "meta": {
        "createdAt": "2025-04-30T09:41:02.053Z",
        "updatedAt": "2025-04-30T09:41:02.053Z",
        "barcode": "3478638588469",
        "qrCode": "https://cdn.dummyjson.com/public/qr-code.png"
      },
      "images": [
        "https://cdn.dummyjson.com/product-images/groceries/eggs/1.webp"
      ],
      "thumbnail": "https://cdn.dummyjson.com/product-images/groceries/eggs/thumbnail.webp",
      "productId": 23,
      "quantity": 1,
      "userId": 1
    },
    {
      "id": "68d6",
      "title": "Beef Steak",
      "description": "High-quality beef steak, great for grilling or cooking to your preferred level of doneness.",
      "category": "groceries",
      "price": 12.99,
      "discountPercentage": 9.61,
      "rating": 4.47,
      "stock": 86,
      "tags": [
        "meat"
      ],
      "sku": "GRO-BRD-BEE-017",
      "weight": 10,
      "dimensions": {
        "width": 18.9,
        "height": 5.77,
        "depth": 18.57
      },
      "warrantyInformation": "3 year warranty",
      "shippingInformation": "Ships overnight",
      "availabilityStatus": "In stock",
      "reviews": [
        {
          "rating": 3,
          "comment": "Would not recommend!",
          "date": "2025-04-30T09:41:02.053Z",
          "reviewerName": "Eleanor Tyler",
          "reviewerEmail": "eleanor.tyler@x.dummyjson.com"
        },
        {
          "rating": 4,
          "comment": "Fast shipping!",
          "date": "2025-04-30T09:41:02.053Z",
          "reviewerName": "Alexander Jones",
          "reviewerEmail": "alexander.jones@x.dummyjson.com"
        },
        {
          "rating": 5,
          "comment": "Great value for money!",
          "date": "2025-04-30T09:41:02.053Z",
          "reviewerName": "Natalie Harris",
          "reviewerEmail": "natalie.harris@x.dummyjson.com"
        }
      ],
      "returnPolicy": "60 days return policy",
      "minimumOrderQuantity": 43,
      "meta": {
        "createdAt": "2025-04-30T09:41:02.053Z",
        "updatedAt": "2025-04-30T09:41:02.053Z",
        "barcode": "5640063409695",
        "qrCode": "https://cdn.dummyjson.com/public/qr-code.png"
      },
      "images": [
        "https://cdn.dummyjson.com/product-images/groceries/beef-steak/1.webp"
      ],
      "thumbnail": "https://cdn.dummyjson.com/product-images/groceries/beef-steak/thumbnail.webp",
      "productId": 17,
      "quantity": 1,
      "userId": 1
    },
    {
      "id": "a727",
      "title": "Eyeshadow Palette with Mirror",
      "description": "The Eyeshadow Palette with Mirror offers a versatile range of eyeshadow shades for creating stunning eye looks. With a built-in mirror, it's convenient for on-the-go makeup application.",
      "category": "beauty",
      "price": 19.99,
      "discountPercentage": 18.19,
      "rating": 2.86,
      "stock": 34,
      "tags": [
        "beauty",
        "eyeshadow"
      ],
      "brand": "Glamour Beauty",
      "sku": "BEA-GLA-EYE-002",
      "weight": 9,
      "dimensions": {
        "width": 9.26,
        "height": 22.47,
        "depth": 27.67
      },
      "warrantyInformation": "1 year warranty",
      "shippingInformation": "Ships in 2 weeks",
      "availabilityStatus": "In stock",
      "reviews": [
        {
          "rating": 5,
          "comment": "Great product!",
          "date": "2025-04-30T09:41:02.053Z",
          "reviewerName": "Savannah Gomez",
          "reviewerEmail": "savannah.gomez@x.dummyjson.com"
        },
        {
          "rating": 4,
          "comment": "Awesome product!",
          "date": "2025-04-30T09:41:02.053Z",
          "reviewerName": "Christian Perez",
          "reviewerEmail": "christian.perez@x.dummyjson.com"
        },
        {
          "rating": 1,
          "comment": "Poor quality!",
          "date": "2025-04-30T09:41:02.053Z",
          "reviewerName": "Nicholas Bailey",
          "reviewerEmail": "nicholas.bailey@x.dummyjson.com"
        }
      ],
      "returnPolicy": "7 days return policy",
      "minimumOrderQuantity": 20,
      "meta": {
        "createdAt": "2025-04-30T09:41:02.053Z",
        "updatedAt": "2025-04-30T09:41:02.053Z",
        "barcode": "9170275171413",
        "qrCode": "https://cdn.dummyjson.com/public/qr-code.png"
      },
      "images": [
        "https://cdn.dummyjson.com/product-images/beauty/eyeshadow-palette-with-mirror/1.webp"
      ],
      "thumbnail": "https://cdn.dummyjson.com/product-images/beauty/eyeshadow-palette-with-mirror/thumbnail.webp",
      "productId": 2,
      "quantity": 1,
      "userId": 1
    },
    {
      "id": "6eed",
      "title": "Powder Canister",
      "description": "The Powder Canister is a finely milled setting powder designed to set makeup and control shine. With a lightweight and translucent formula, it provides a smooth and matte finish.",
      "category": "beauty",
      "price": 14.99,
      "discountPercentage": 9.84,
      "rating": 4.64,
      "stock": 89,
      "tags": [
        "beauty",
        "face powder"
      ],
      "brand": "Velvet Touch",
      "sku": "BEA-VEL-POW-003",
      "weight": 8,
      "dimensions": {
        "width": 29.27,
        "height": 27.93,
        "depth": 20.59
      },
      "warrantyInformation": "3 months warranty",
      "shippingInformation": "Ships in 1-2 business days",
      "availabilityStatus": "In stock",
      "reviews": [
        {
          "rating": 4,
          "comment": "Would buy again!",
          "date": "2025-04-30T09:41:02.053Z",
          "reviewerName": "Alexander Jones",
          "reviewerEmail": "alexander.jones@x.dummyjson.com"
        },
        {
          "rating": 5,
          "comment": "Highly impressed!",
          "date": "2025-04-30T09:41:02.053Z",
          "reviewerName": "Elijah Cruz",
          "reviewerEmail": "elijah.cruz@x.dummyjson.com"
        },
        {
          "rating": 1,
          "comment": "Very dissatisfied!",
          "date": "2025-04-30T09:41:02.053Z",
          "reviewerName": "Avery Perez",
          "reviewerEmail": "avery.perez@x.dummyjson.com"
        }
      ],
      "returnPolicy": "No return policy",
      "minimumOrderQuantity": 22,
      "meta": {
        "createdAt": "2025-04-30T09:41:02.053Z",
        "updatedAt": "2025-04-30T09:41:02.053Z",
        "barcode": "8418883906837",
        "qrCode": "https://cdn.dummyjson.com/public/qr-code.png"
      },
      "images": [
        "https://cdn.dummyjson.com/product-images/beauty/powder-canister/1.webp"
      ],
      "thumbnail": "https://cdn.dummyjson.com/product-images/beauty/powder-canister/thumbnail.webp",
      "productId": 3,
      "quantity": 1,
      "userId": 1
    },
    {
      "id": "1bef",
      "title": "Red Lipstick",
      "description": "The Red Lipstick is a classic and bold choice for adding a pop of color to your lips. With a creamy and pigmented formula, it provides a vibrant and long-lasting finish.",
      "category": "beauty",
      "price": 12.99,
      "discountPercentage": 12.16,
      "rating": 4.36,
      "stock": 91,
      "tags": [
        "beauty",
        "lipstick"
      ],
      "brand": "Chic Cosmetics",
      "sku": "BEA-CHI-LIP-004",
      "weight": 1,
      "dimensions": {
        "width": 18.11,
        "height": 28.38,
        "depth": 22.17
      },
      "warrantyInformation": "3 year warranty",
      "shippingInformation": "Ships in 1 week",
      "availabilityStatus": "In stock",
      "reviews": [
        {
          "rating": 4,
          "comment": "Great product!",
          "date": "2025-04-30T09:41:02.053Z",
          "reviewerName": "Liam Garcia",
          "reviewerEmail": "liam.garcia@x.dummyjson.com"
        },
        {
          "rating": 5,
          "comment": "Great product!",
          "date": "2025-04-30T09:41:02.053Z",
          "reviewerName": "Ruby Andrews",
          "reviewerEmail": "ruby.andrews@x.dummyjson.com"
        },
        {
          "rating": 5,
          "comment": "Would buy again!",
          "date": "2025-04-30T09:41:02.053Z",
          "reviewerName": "Clara Berry",
          "reviewerEmail": "clara.berry@x.dummyjson.com"
        }
      ],
      "returnPolicy": "7 days return policy",
      "minimumOrderQuantity": 40,
      "meta": {
        "createdAt": "2025-04-30T09:41:02.053Z",
        "updatedAt": "2025-04-30T09:41:02.053Z",
        "barcode": "9467746727219",
        "qrCode": "https://cdn.dummyjson.com/public/qr-code.png"
      },
      "images": [
        "https://cdn.dummyjson.com/product-images/beauty/red-lipstick/1.webp"
      ],
      "thumbnail": "https://cdn.dummyjson.com/product-images/beauty/red-lipstick/thumbnail.webp",
      "productId": 4,
      "quantity": 1,
      "userId": 1
    },
    {
      "id": "5e8b",
      "title": "iPhone 6",
      "description": "The iPhone 6 is a stylish and capable smartphone with a larger display and improved performance. It introduced new features and design elements, making it a popular choice in its time.",
      "category": "smartphones",
      "price": 299.99,
      "discountPercentage": 6.69,
      "rating": 3.41,
      "stock": 60,
      "tags": [
        "smartphones",
        "apple"
      ],
      "brand": "Apple",
      "sku": "SMA-APP-IPH-122",
      "weight": 7,
      "dimensions": {
        "width": 11,
        "height": 9.1,
        "depth": 9.67
      },
      "warrantyInformation": "1 month warranty",
      "shippingInformation": "Ships overnight",
      "availabilityStatus": "In stock",
      "reviews": [
        {
          "rating": 3,
          "comment": "Disappointing product!",
          "date": "2025-04-30T09:41:02.054Z",
          "reviewerName": "Stella Morris",
          "reviewerEmail": "stella.morris@x.dummyjson.com"
        },
        {
          "rating": 4,
          "comment": "Excellent quality!",
          "date": "2025-04-30T09:41:02.054Z",
          "reviewerName": "Nolan Gonzalez",
          "reviewerEmail": "nolan.gonzalez@x.dummyjson.com"
        },
        {
          "rating": 5,
          "comment": "Great value for money!",
          "date": "2025-04-30T09:41:02.054Z",
          "reviewerName": "Benjamin Foster",
          "reviewerEmail": "benjamin.foster@x.dummyjson.com"
        }
      ],
      "returnPolicy": "7 days return policy",
      "minimumOrderQuantity": 5,
      "meta": {
        "createdAt": "2025-04-30T09:41:02.054Z",
        "updatedAt": "2025-04-30T09:41:02.054Z",
        "barcode": "9922357685013",
        "qrCode": "https://cdn.dummyjson.com/public/qr-code.png"
      },
      "images": [
        "https://cdn.dummyjson.com/product-images/smartphones/iphone-6/1.webp",
        "https://cdn.dummyjson.com/product-images/smartphones/iphone-6/2.webp",
        "https://cdn.dummyjson.com/product-images/smartphones/iphone-6/3.webp"
      ],
      "thumbnail": "https://cdn.dummyjson.com/product-images/smartphones/iphone-6/thumbnail.webp",
      "productId": 122,
      "quantity": 1,
      "userId": 1
    },
    {
      "id": "aede",
      "title": "iPhone 13 Pro",
      "description": "The iPhone 13 Pro is a cutting-edge smartphone with a powerful camera system, high-performance chip, and stunning display. It offers advanced features for users who demand top-notch technology.",
      "category": "smartphones",
      "price": 1099.99,
      "discountPercentage": 9.37,
      "rating": 4.12,
      "stock": 56,
      "tags": [
        "smartphones",
        "apple"
      ],
      "brand": "Apple",
      "sku": "SMA-APP-IPH-123",
      "weight": 8,
      "dimensions": {
        "width": 12.63,
        "height": 5.28,
        "depth": 14.29
      },
      "warrantyInformation": "3 year warranty",
      "shippingInformation": "Ships in 2 weeks",
      "availabilityStatus": "In stock",
      "reviews": [
        {
          "rating": 5,
          "comment": "Would buy again!",
          "date": "2025-04-30T09:41:02.054Z",
          "reviewerName": "Christian Perez",
          "reviewerEmail": "christian.perez@x.dummyjson.com"
        },
        {
          "rating": 3,
          "comment": "Not worth the price!",
          "date": "2025-04-30T09:41:02.054Z",
          "reviewerName": "Liam Gonzalez",
          "reviewerEmail": "liam.gonzalez@x.dummyjson.com"
        },
        {
          "rating": 5,
          "comment": "Very satisfied!",
          "date": "2025-04-30T09:41:02.054Z",
          "reviewerName": "Tristan Scott",
          "reviewerEmail": "tristan.scott@x.dummyjson.com"
        }
      ],
      "returnPolicy": "7 days return policy",
      "minimumOrderQuantity": 1,
      "meta": {
        "createdAt": "2025-04-30T09:41:02.054Z",
        "updatedAt": "2025-04-30T09:41:02.054Z",
        "barcode": "4998438802308",
        "qrCode": "https://cdn.dummyjson.com/public/qr-code.png"
      },
      "images": [
        "https://cdn.dummyjson.com/product-images/smartphones/iphone-13-pro/1.webp",
        "https://cdn.dummyjson.com/product-images/smartphones/iphone-13-pro/2.webp",
        "https://cdn.dummyjson.com/product-images/smartphones/iphone-13-pro/3.webp"
      ],
      "thumbnail": "https://cdn.dummyjson.com/product-images/smartphones/iphone-13-pro/thumbnail.webp",
      "productId": 123,
      "quantity": 1,
      "userId": 1
    },
    {
      "id": "7892",
      "title": "iPhone X",
      "description": "The iPhone X is a flagship smartphone featuring a bezel-less OLED display, facial recognition technology (Face ID), and impressive performance. It represents a milestone in iPhone design and innovation.",
      "category": "smartphones",
      "price": 899.99,
      "discountPercentage": 19.59,
      "rating": 2.51,
      "stock": 37,
      "tags": [
        "smartphones",
        "apple"
      ],
      "brand": "Apple",
      "sku": "SMA-APP-IPH-124",
      "weight": 1,
      "dimensions": {
        "width": 21.88,
        "height": 24.19,
        "depth": 14.19
      },
      "warrantyInformation": "3 months warranty",
      "shippingInformation": "Ships in 3-5 business days",
      "availabilityStatus": "In stock",
      "reviews": [
        {
          "rating": 4,
          "comment": "Highly recommended!",
          "date": "2025-04-30T09:41:02.054Z",
          "reviewerName": "Tyler Davis",
          "reviewerEmail": "tyler.davis@x.dummyjson.com"
        },
        {
          "rating": 5,
          "comment": "Great product!",
          "date": "2025-04-30T09:41:02.054Z",
          "reviewerName": "Aria Parker",
          "reviewerEmail": "aria.parker@x.dummyjson.com"
        },
        {
          "rating": 2,
          "comment": "Not as described!",
          "date": "2025-04-30T09:41:02.054Z",
          "reviewerName": "Lily Torres",
          "reviewerEmail": "lily.torres@x.dummyjson.com"
        }
      ],
      "returnPolicy": "7 days return policy",
      "minimumOrderQuantity": 2,
      "meta": {
        "createdAt": "2025-04-30T09:41:02.054Z",
        "updatedAt": "2025-04-30T09:41:02.054Z",
        "barcode": "3034949322264",
        "qrCode": "https://cdn.dummyjson.com/public/qr-code.png"
      },
      "images": [
        "https://cdn.dummyjson.com/product-images/smartphones/iphone-x/1.webp",
        "https://cdn.dummyjson.com/product-images/smartphones/iphone-x/2.webp",
        "https://cdn.dummyjson.com/product-images/smartphones/iphone-x/3.webp"
      ],
      "thumbnail": "https://cdn.dummyjson.com/product-images/smartphones/iphone-x/thumbnail.webp",
      "productId": 124,
      "quantity": 1,
      "userId": 1
    },
    {
      "id": "9995",
      "title": "Oppo A57",
      "description": "The Oppo A57 is a mid-range smartphone known for its sleek design and capable features. It offers a balance of performance and affordability, making it a popular choice.",
      "category": "smartphones",
      "price": 249.99,
      "discountPercentage": 2.43,
      "rating": 3.94,
      "stock": 19,
      "tags": [
        "smartphones",
        "oppo"
      ],
      "brand": "Oppo",
      "sku": "SMA-OPP-OPP-125",
      "weight": 5,
      "dimensions": {
        "width": 7.2,
        "height": 10.74,
        "depth": 23.68
      },
      "warrantyInformation": "Lifetime warranty",
      "shippingInformation": "Ships in 3-5 business days",
      "availabilityStatus": "In stock",
      "reviews": [
        {
          "rating": 4,
          "comment": "Excellent quality!",
          "date": "2025-04-30T09:41:02.054Z",
          "reviewerName": "Scarlett Wright",
          "reviewerEmail": "scarlett.wright@x.dummyjson.com"
        },
        {
          "rating": 5,
          "comment": "Excellent quality!",
          "date": "2025-04-30T09:41:02.054Z",
          "reviewerName": "Jacob Cooper",
          "reviewerEmail": "jacob.cooper@x.dummyjson.com"
        },
        {
          "rating": 2,
          "comment": "Poor quality!",
          "date": "2025-04-30T09:41:02.054Z",
          "reviewerName": "Zoe Nicholson",
          "reviewerEmail": "zoe.nicholson@x.dummyjson.com"
        }
      ],
      "returnPolicy": "90 days return policy",
      "minimumOrderQuantity": 3,
      "meta": {
        "createdAt": "2025-04-30T09:41:02.054Z",
        "updatedAt": "2025-04-30T09:41:02.054Z",
        "barcode": "0651223722522",
        "qrCode": "https://cdn.dummyjson.com/public/qr-code.png"
      },
      "images": [
        "https://cdn.dummyjson.com/product-images/smartphones/oppo-a57/1.webp",
        "https://cdn.dummyjson.com/product-images/smartphones/oppo-a57/2.webp",
        "https://cdn.dummyjson.com/product-images/smartphones/oppo-a57/3.webp"
      ],
      "thumbnail": "https://cdn.dummyjson.com/product-images/smartphones/oppo-a57/thumbnail.webp",
      "productId": 125,
      "quantity": 1,
      "userId": 1
    }
  ],
  "address": [
    {
      "id": "00b6",
      "fullName": "sqqqq",
      "mobile": "qqqqqq",
      "addressLine1": "qqqqqqqqqqq",
      "area": "qqqq",
      "landmark": "qqqq",
      "city": "qqqq",
      "state": "qqqq",
      "pincode": "qqqq",
      "addressType": "other"
    },
    {
      "fullName": "1111",
      "mobile": "111111",
      "addressLine1": "dedwewedwwwwwwwwww",
      "area": "11",
      "landmark": null,
      "city": "sssssssssssssss",
      "state": "4545454545",
      "pincode": "d34543534543",
      "addressType": "home",
      "id": "3afe"
    }
  ],
  "wishlist": [
    {
      "id": "5d84",
      "productId": 122
    },
    {
      "id": "3509",
      "productId": 4
    },
    {
      "id": "8173",
      "productId": 130
    },
    {
      "id": "d5fd",
      "productId": 12
    },
    {
      "id": "fbfc",
      "productId": 3
    },
    {
      "id": "457e",
      "productId": 123
    },
    {
      "id": "3612",
      "productId": 124
    },
    {
      "id": "7f81",
      "productId": 125
    }
  ],
  "orders": [
    {
      "id": "584a",
      "userId": 1,
      "addressId": null,
      "orderDate": "2025-12-22T07:43:11.861Z",
      "status": "PLACED",
      "paymentMode": "Online",
      "totalAmount": 2365.97444738,
      "orderItems": [
        {
          "productId": 3,
          "name": "Powder Canister",
          "image": "https://cdn.dummyjson.com/product-images/beauty/powder-canister/thumbnail.webp",
          "quantity": 3,
          "finalPrice": 44.97
        },
        {
          "productId": 124,
          "name": "iPhone X",
          "image": "https://cdn.dummyjson.com/product-images/smartphones/iphone-x/thumbnail.webp",
          "quantity": 1,
          "finalPrice": 899.99
        },
        {
          "productId": 125,
          "name": "Oppo A57",
          "image": "https://cdn.dummyjson.com/product-images/smartphones/oppo-a57/thumbnail.webp",
          "quantity": 1,
          "finalPrice": 249.99
        },
        {
          "productId": 123,
          "name": "iPhone 13 Pro",
          "image": "https://cdn.dummyjson.com/product-images/smartphones/iphone-13-pro/thumbnail.webp",
          "quantity": 1,
          "finalPrice": 1099.99
        }
      ]
    },
    {
      "id": "0db4",
      "userId": 1,
      "addressId": null,
      "orderDate": "2025-12-22T07:53:53.141Z",
      "status": "PLACED",
      "paymentMode": "Online",
      "totalAmount": 6300.498238659999,
      "orderItems": [
        {
          "productId": 11,
          "name": "Annibale Colombo Bed",
          "image": "https://cdn.dummyjson.com/product-images/furniture/annibale-colombo-bed/thumbnail.webp",
          "quantity": 1,
          "finalPrice": 1899.99
        },
        {
          "productId": 12,
          "name": "Annibale Colombo Sofa",
          "image": "https://cdn.dummyjson.com/product-images/furniture/annibale-colombo-sofa/thumbnail.webp",
          "quantity": 1,
          "finalPrice": 2499.99
        },
        {
          "productId": 13,
          "name": "Bedside Table African Cherry",
          "image": "https://cdn.dummyjson.com/product-images/furniture/bedside-table-african-cherry/thumbnail.webp",
          "quantity": 1,
          "finalPrice": 299.99
        },
        {
          "productId": 14,
          "name": "Knoll Saarinen Executive Conference Chair",
          "image": "https://cdn.dummyjson.com/product-images/furniture/knoll-saarinen-executive-conference-chair/thumbnail.webp",
          "quantity": 1,
          "finalPrice": 499.99
        },
        {
          "productId": 15,
          "name": "Wooden Bathroom Sink With Mirror",
          "image": "https://cdn.dummyjson.com/product-images/furniture/wooden-bathroom-sink-with-mirror/thumbnail.webp",
          "quantity": 1,
          "finalPrice": 799.99
        }
      ]
    },
    {
      "id": "570d",
      "userId": 1,
      "addressId": null,
      "orderDate": "2025-12-22T08:47:21.100Z",
      "status": "PLACED",
      "paymentMode": "Online",
      "totalAmount": 2648.43779344,
      "orderItems": [
        {
          "productId": 123,
          "name": "iPhone 13 Pro",
          "image": "https://cdn.dummyjson.com/product-images/smartphones/iphone-13-pro/thumbnail.webp",
          "quantity": 1,
          "finalPrice": 1099.99
        },
        {
          "productId": 124,
          "name": "iPhone X",
          "image": "https://cdn.dummyjson.com/product-images/smartphones/iphone-x/thumbnail.webp",
          "quantity": 1,
          "finalPrice": 899.99
        },
        {
          "productId": 125,
          "name": "Oppo A57",
          "image": "https://cdn.dummyjson.com/product-images/smartphones/oppo-a57/thumbnail.webp",
          "quantity": 1,
          "finalPrice": 249.99
        },
        {
          "productId": 122,
          "name": "iPhone 6",
          "image": "https://cdn.dummyjson.com/product-images/smartphones/iphone-6/thumbnail.webp",
          "quantity": 1,
          "finalPrice": 299.99
        }
      ]
    },
    {
      "id": "3bff",
      "userId": 1,
      "addressId": null,
      "orderDate": "2025-12-22T08:52:45.439Z",
      "status": "PLACED",
      "paymentMode": "Online",
      "totalAmount": 1104.8543963000002,
      "orderItems": [
        {
          "productId": 7,
          "name": "Chanel Coco Noir Eau De",
          "image": "https://cdn.dummyjson.com/product-images/fragrances/chanel-coco-noir-eau-de/thumbnail.webp",
          "quantity": 1,
          "finalPrice": 129.99
        },
        {
          "productId": 8,
          "name": "Dior J'adore",
          "image": "https://cdn.dummyjson.com/product-images/fragrances/dior-j'adore/thumbnail.webp",
          "quantity": 1,
          "finalPrice": 89.99
        },
        {
          "productId": 13,
          "name": "Bedside Table African Cherry",
          "image": "https://cdn.dummyjson.com/product-images/furniture/bedside-table-african-cherry/thumbnail.webp",
          "quantity": 1,
          "finalPrice": 299.99
        },
        {
          "productId": 14,
          "name": "Knoll Saarinen Executive Conference Chair",
          "image": "https://cdn.dummyjson.com/product-images/furniture/knoll-saarinen-executive-conference-chair/thumbnail.webp",
          "quantity": 1,
          "finalPrice": 499.99
        },
        {
          "productId": 22,
          "name": "Dog Food",
          "image": "https://cdn.dummyjson.com/product-images/groceries/dog-food/thumbnail.webp",
          "quantity": 1,
          "finalPrice": 10.99
        },
        {
          "productId": 28,
          "name": "Ice Cream",
          "image": "https://cdn.dummyjson.com/product-images/groceries/ice-cream/thumbnail.webp",
          "quantity": 1,
          "finalPrice": 5.49
        },
        {
          "productId": 29,
          "name": "Juice",
          "image": "https://cdn.dummyjson.com/product-images/groceries/juice/thumbnail.webp",
          "quantity": 1,
          "finalPrice": 3.99
        }
      ]
    },
    {
      "id": "40d6",
      "userId": 1,
      "addressId": null,
      "orderDate": "2025-12-22T09:03:50.623Z",
      "status": "PLACED",
      "paymentMode": "Online",
      "totalAmount": 8260.175663059998,
      "orderItems": [
        {
          "productId": 130,
          "name": "Realme XT",
          "image": "https://cdn.dummyjson.com/product-images/smartphones/realme-xt/thumbnail.webp",
          "quantity": 1,
          "finalPrice": 349.99
        },
        {
          "productId": 12,
          "name": "Annibale Colombo Sofa",
          "image": "https://cdn.dummyjson.com/product-images/furniture/annibale-colombo-sofa/thumbnail.webp",
          "quantity": 3,
          "finalPrice": 7499.969999999999
        },
        {
          "productId": 13,
          "name": "Bedside Table African Cherry",
          "image": "https://cdn.dummyjson.com/product-images/furniture/bedside-table-african-cherry/thumbnail.webp",
          "quantity": 1,
          "finalPrice": 299.99
        },
        {
          "productId": 18,
          "name": "Cat Food",
          "image": "https://cdn.dummyjson.com/product-images/groceries/cat-food/thumbnail.webp",
          "quantity": 1,
          "finalPrice": 8.99
        },
        {
          "productId": 19,
          "name": "Chicken Meat",
          "image": "https://cdn.dummyjson.com/product-images/groceries/chicken-meat/thumbnail.webp",
          "quantity": 1,
          "finalPrice": 9.99
        },
        {
          "productId": 27,
          "name": "Honey Jar",
          "image": "https://cdn.dummyjson.com/product-images/groceries/honey-jar/thumbnail.webp",
          "quantity": 1,
          "finalPrice": 6.99
        },
        {
          "productId": 28,
          "name": "Ice Cream",
          "image": "https://cdn.dummyjson.com/product-images/groceries/ice-cream/thumbnail.webp",
          "quantity": 1,
          "finalPrice": 5.49
        }
      ]
    },
    {
      "id": "96f6",
      "userId": 1,
      "addressId": null,
      "orderDate": "2025-12-22T09:10:12.262Z",
      "status": "PLACED",
      "paymentMode": "Online",
      "totalAmount": 8825.965889799996,
      "orderItems": [
        {
          "productId": 123,
          "name": "iPhone 13 Pro",
          "image": "https://cdn.dummyjson.com/product-images/smartphones/iphone-13-pro/thumbnail.webp",
          "quantity": 1,
          "finalPrice": 1099.99
        },
        {
          "productId": 124,
          "name": "iPhone X",
          "image": "https://cdn.dummyjson.com/product-images/smartphones/iphone-x/thumbnail.webp",
          "quantity": 1,
          "finalPrice": 899.99
        },
        {
          "productId": 125,
          "name": "Oppo A57",
          "image": "https://cdn.dummyjson.com/product-images/smartphones/oppo-a57/thumbnail.webp",
          "quantity": 1,
          "finalPrice": 249.99
        },
        {
          "productId": 128,
          "name": "Realme C35",
          "image": "https://cdn.dummyjson.com/product-images/smartphones/realme-c35/thumbnail.webp",
          "quantity": 1,
          "finalPrice": 149.99
        },
        {
          "productId": 129,
          "name": "Realme X",
          "image": "https://cdn.dummyjson.com/product-images/smartphones/realme-x/thumbnail.webp",
          "quantity": 1,
          "finalPrice": 299.99
        },
        {
          "productId": 130,
          "name": "Realme XT",
          "image": "https://cdn.dummyjson.com/product-images/smartphones/realme-xt/thumbnail.webp",
          "quantity": 1,
          "finalPrice": 349.99
        },
        {
          "productId": 127,
          "name": "Oppo K1",
          "image": "https://cdn.dummyjson.com/product-images/smartphones/oppo-k1/thumbnail.webp",
          "quantity": 1,
          "finalPrice": 299.99
        },
        {
          "productId": 121,
          "name": "iPhone 5s",
          "image": "https://cdn.dummyjson.com/product-images/smartphones/iphone-5s/thumbnail.webp",
          "quantity": 1,
          "finalPrice": 199.99
        },
        {
          "productId": 12,
          "name": "Annibale Colombo Sofa",
          "image": "https://cdn.dummyjson.com/product-images/furniture/annibale-colombo-sofa/thumbnail.webp",
          "quantity": 1,
          "finalPrice": 2499.99
        },
        {
          "productId": 22,
          "name": "Dog Food",
          "image": "https://cdn.dummyjson.com/product-images/groceries/dog-food/thumbnail.webp",
          "quantity": 1,
          "finalPrice": 10.99
        },
        {
          "productId": 23,
          "name": "Eggs",
          "image": "https://cdn.dummyjson.com/product-images/groceries/eggs/thumbnail.webp",
          "quantity": 1,
          "finalPrice": 2.99
        },
        {
          "productId": 17,
          "name": "Beef Steak",
          "image": "https://cdn.dummyjson.com/product-images/groceries/beef-steak/thumbnail.webp",
          "quantity": 1,
          "finalPrice": 12.99
        },
        {
          "productId": 3,
          "name": "Powder Canister",
          "image": "https://cdn.dummyjson.com/product-images/beauty/powder-canister/thumbnail.webp",
          "quantity": 1,
          "finalPrice": 14.99
        },
        {
          "productId": 2,
          "name": "Eyeshadow Palette with Mirror",
          "image": "https://cdn.dummyjson.com/product-images/beauty/eyeshadow-palette-with-mirror/thumbnail.webp",
          "quantity": 1,
          "finalPrice": 19.99
        },
        {
          "productId": 4,
          "name": "Red Lipstick",
          "image": "https://cdn.dummyjson.com/product-images/beauty/red-lipstick/thumbnail.webp",
          "quantity": 1,
          "finalPrice": 12.99
        },
        {
          "productId": 5,
          "name": "Red Nail Polish",
          "image": "https://cdn.dummyjson.com/product-images/beauty/red-nail-polish/thumbnail.webp",
          "quantity": 1,
          "finalPrice": 8.99
        },
        {
          "productId": 8,
          "name": "Dior J'adore",
          "image": "https://cdn.dummyjson.com/product-images/fragrances/dior-j'adore/thumbnail.webp",
          "quantity": 1,
          "finalPrice": 89.99
        },
        {
          "productId": 7,
          "name": "Chanel Coco Noir Eau De",
          "image": "https://cdn.dummyjson.com/product-images/fragrances/chanel-coco-noir-eau-de/thumbnail.webp",
          "quantity": 1,
          "finalPrice": 129.99
        },
        {
          "productId": 13,
          "name": "Bedside Table African Cherry",
          "image": "https://cdn.dummyjson.com/product-images/furniture/bedside-table-african-cherry/thumbnail.webp",
          "quantity": 1,
          "finalPrice": 299.99
        },
        {
          "productId": 14,
          "name": "Knoll Saarinen Executive Conference Chair",
          "image": "https://cdn.dummyjson.com/product-images/furniture/knoll-saarinen-executive-conference-chair/thumbnail.webp",
          "quantity": 2,
          "finalPrice": 999.98
        },
        {
          "productId": 15,
          "name": "Wooden Bathroom Sink With Mirror",
          "image": "https://cdn.dummyjson.com/product-images/furniture/wooden-bathroom-sink-with-mirror/thumbnail.webp",
          "quantity": 1,
          "finalPrice": 799.99
        },
        {
          "productId": 18,
          "name": "Cat Food",
          "image": "https://cdn.dummyjson.com/product-images/groceries/cat-food/thumbnail.webp",
          "quantity": 1,
          "finalPrice": 8.99
        },
        {
          "productId": 25,
          "name": "Green Bell Pepper",
          "image": "https://cdn.dummyjson.com/product-images/groceries/green-bell-pepper/thumbnail.webp",
          "quantity": 3,
          "finalPrice": 3.87
        },
        {
          "productId": 27,
          "name": "Honey Jar",
          "image": "https://cdn.dummyjson.com/product-images/groceries/honey-jar/thumbnail.webp",
          "quantity": 2,
          "finalPrice": 13.98
        },
        {
          "productId": 28,
          "name": "Ice Cream",
          "image": "https://cdn.dummyjson.com/product-images/groceries/ice-cream/thumbnail.webp",
          "quantity": 1,
          "finalPrice": 5.49
        }
      ]
    }
  ]
}